{
  "gymBro": {
    "health": 70,
    "baseAttack": 20,
    "speed": 120
  },
  "heracles": {
    "health": 70,
    "baseAttack": 20,
    "speed": 120
  },

  "poops": {
    "health": 70,
    "baseAttack": 20,
    "speed": 120
  },

  "oneLegGirl": {
    "health": 1,
    "baseAttack": 0
  },
  "plug": {
    "health": 1,
    "baseAttack": 0
  },

  "child": {
    "health": 1,
    "baseAttack": 0
  },
  "guard": {
    "health": 1,
    "baseAttack": 0
  },
  "male_citizen": {
    "health": 1,
    "baseAttack": 0
  }
}
